{"pixiv_pic": [{"name": "116711913", "path": "./pixiv/2024-03-10-14-02-32/116711913.jpg", "index": 0, "user": "ttosom", "ext": ".jpg"}, {"name": "116711996", "path": "./pixiv/2024-03-10-14-02-32/116711996.jpg", "index": 1, "user": "\u9632\u4eba", "ext": ".jpg"}, {"name": "116737543", "path": "./pixiv/2024-03-10-14-02-32/116737543.png", "index": 2, "user": "\u30a2\u30ea\u30af\u30a4\u306e\u30a4\u30ab\u30af", "ext": ".png"}, {"name": "116740771", "path": "./pixiv/2024-03-10-14-02-32/116740771.png", "index": 3, "user": "\u795e\u61762JINKEI", "ext": ".png"}, {"name": "116740213", "path": "./pixiv/2024-03-10-14-02-32/116740213.jpg", "index": 4, "user": "\u30b9\u30b3\u30c3\u30c6\u30a3", "ext": ".jpg"}, {"name": "116712238", "path": "./pixiv/2024-03-10-14-02-32/116712238.png", "index": 5, "user": "\u829d", "ext": ".png"}, {"name": "116740173", "path": "./pixiv/2024-03-10-14-02-32/116740173.jpg", "index": 6, "user": "iren", "ext": ".jpg"}, {"name": "116741478", "path": "./pixiv/2024-03-10-14-02-32/116741478.jpg", "index": 7, "user": "\u30ab\u30d5\u30a7", "ext": ".jpg"}, {"name": "116752505", "path": "./pixiv/2024-03-10-14-02-32/116752505.jpg", "index": 8, "user": "Saclia", "ext": ".jpg"}, {"name": "116741622", "path": "./pixiv/2024-03-10-14-02-32/116741622.jpg", "index": 9, "user": "\u5343\u591cQYS3", "ext": ".jpg"}, {"name": "116743656", "path": "./pixiv/2024-03-10-14-02-32/116743656.jpg", "index": 10, "user": "Criin", "ext": ".jpg"}, {"name": "116754389", "path": "./pixiv/2024-03-10-14-02-32/116754389.png", "index": 11, "user": "\u9262\u4eba", "ext": ".png"}, {"name": "116740428", "path": "./pixiv/2024-03-10-14-02-32/116740428.png", "index": 12, "user": "KANOSE", "ext": ".png"}, {"name": "116711951", "path": "./pixiv/2024-03-10-14-02-32/116711951.jpg", "index": 13, "user": "\u30a6\u30e9", "ext": ".jpg"}, {"name": "116732320", "path": "./pixiv/2024-03-10-14-02-32/116732320.png", "index": 14, "user": "\u30a6\u30c8\u30ea", "ext": ".png"}, {"name": "116744396", "path": "./pixiv/2024-03-10-14-02-32/116744396.png", "index": 15, "user": "Lpip", "ext": ".png"}, {"name": "116718880", "path": "./pixiv/2024-03-10-14-02-32/116718880.jpg", "index": 16, "user": "Toy(e)", "ext": ".jpg"}, {"name": "116712631", "path": "./pixiv/2024-03-10-14-02-32/116712631.jpg", "index": 17, "user": "TAYA", "ext": ".jpg"}, {"name": "116771401", "path": "./pixiv/2024-03-10-14-02-32/116771401.jpg", "index": 18, "user": "\u304b\u308f\u3084\u3070\u3050", "ext": ".jpg"}, {"name": "116757906", "path": "./pixiv/2024-03-10-14-02-32/116757906.jpg", "index": 19, "user": "EEJU", "ext": ".jpg"}, {"name": "116767025", "path": "./pixiv/2024-03-10-14-02-32/116767025.png", "index": 20, "user": "\u62a0\u8089\u809a\u8110@Kuroduki", "ext": ".png"}, {"name": "116740690", "path": "./pixiv/2024-03-10-14-02-32/116740690.jpg", "index": 21, "user": "\u3090\u900f", "ext": ".jpg"}, {"name": "116741033", "path": "./pixiv/2024-03-10-14-02-32/116741033.jpg", "index": 22, "user": "Rella", "ext": ".jpg"}, {"name": "116747608", "path": "./pixiv/2024-03-10-14-02-32/116747608.jpg", "index": 23, "user": "\u6f2b\u753b\u7d20\u6750\u5de5\u623f", "ext": ".jpg"}, {"name": "116740326", "path": "./pixiv/2024-03-10-14-02-32/116740326.jpg", "index": 24, "user": "\u7518\u6728\u82b1", "ext": ".jpg"}, {"name": "116711954", "path": "./pixiv/2024-03-10-14-02-32/116711954.png", "index": 25, "user": "\u82b1\u30f6\u7530111hanagata", "ext": ".png"}, {"name": "116754237", "path": "./pixiv/2024-03-10-14-02-32/116754237.jpg", "index": 26, "user": "makoron117", "ext": ".jpg"}, {"name": "116742446", "path": "./pixiv/2024-03-10-14-02-32/116742446.jpg", "index": 27, "user": "Rumoon", "ext": ".jpg"}, {"name": "116740413", "path": "./pixiv/2024-03-10-14-02-32/116740413.jpg", "index": 28, "user": "\u3042\u308b\u3066\u3089", "ext": ".jpg"}, {"name": "116740912", "path": "./pixiv/2024-03-10-14-02-32/116740912.png", "index": 29, "user": "PiPi", "ext": ".png"}, {"name": "116740385", "path": "./pixiv/2024-03-10-14-02-32/116740385.png", "index": 30, "user": "\u4e0a\u5009\u30a8\u30af", "ext": ".png"}, {"name": "116743519", "path": "./pixiv/2024-03-10-14-02-32/116743519.jpg", "index": 31, "user": "majamari", "ext": ".jpg"}, {"name": "116711920", "path": "./pixiv/2024-03-10-14-02-32/116711920.jpg", "index": 32, "user": "NE\u00d8N", "ext": ".jpg"}, {"name": "116721610", "path": "./pixiv/2024-03-10-14-02-32/116721610.jpg", "index": 33, "user": "\u30c4\u30f3\u30a4\u30c1", "ext": ".jpg"}, {"name": "116719569", "path": "./pixiv/2024-03-10-14-02-32/116719569.jpg", "index": 34, "user": "\u5ddd\u53e3\u30a4\u30c3\u30b5", "ext": ".jpg"}, {"name": "116763500", "path": "./pixiv/2024-03-10-14-02-32/116763500.jpg", "index": 35, "user": "\u7d3a\u5c4b\u9d09\u6c5f", "ext": ".jpg"}, {"name": "116759875", "path": "./pixiv/2024-03-10-14-02-32/116759875.jpg", "index": 36, "user": "\u9ece\uff08\u30af\u30ed\u30a4\uff09", "ext": ".jpg"}, {"name": "116722445", "path": "./pixiv/2024-03-10-14-02-32/116722445.jpg", "index": 37, "user": "\u3072\u3065\u308b\u3081(Hidzzz)", "ext": ".jpg"}, {"name": "116732891", "path": "./pixiv/2024-03-10-14-02-32/116732891.jpg", "index": 38, "user": "\u8429\u68ee\u3058\u3042", "ext": ".jpg"}, {"name": "116767564", "path": "./pixiv/2024-03-10-14-02-32/116767564.png", "index": 39, "user": "\u30ca\u30e9\u306a\u304d\u308a", "ext": ".png"}, {"name": "116742197", "path": "./pixiv/2024-03-10-14-02-32/116742197.jpg", "index": 40, "user": "\u6b50MIN", "ext": ".jpg"}, {"name": "116745577", "path": "./pixiv/2024-03-10-14-02-32/116745577.jpg", "index": 41, "user": "Sa-fu", "ext": ".jpg"}, {"name": "116740150", "path": "./pixiv/2024-03-10-14-02-32/116740150.jpg", "index": 42, "user": "\u304b\u3089\u306a\u304c\u308c", "ext": ".jpg"}]}